[
  {
    "id": "mein-schiff-4-0105",
    "date": "2026-05-01",
    "ship": "Mein Schiff 4",
    "company": "TUI",
    "arrival": "04:00",
    "departure": "22:00"
  },
  {
    "id": "silver-ray-0105",
    "date": "2026-05-01",
    "ship": "Silver Ray",
    "company": "Silversea",
    "arrival": "08:00",
    "departure": "22:00"
  },
  {
    "id": "ritz-carlton-evrima-0105",
    "date": "2026-05-01",
    "ship": "Ritz-Carlton Evrima",
    "company": "Ritz-Carlton",
    "arrival": "08:00",
    "departure": "22:00"
  },
  {
    "id": "aidacosma-0205",
    "date": "2026-05-02",
    "ship": "AIDAcosma",
    "company": "AIDA",
    "arrival": "05:00",
    "departure": "22:00"
  },
  {
    "id": "marella-explorer-0205",
    "date": "2026-05-02",
    "ship": "Marella Explorer",
    "company": "Marella",
    "arrival": "06:00",
    "departure": "22:00"
  },
  {
    "id": "norwegian-epic-0205",
    "date": "2026-05-02",
    "ship": "Norwegian Epic",
    "company": "Norwegian",
    "arrival": "07:00",
    "departure": "18:00"
  },
  {
    "id": "mein-schiff-1-0305",
    "date": "2026-05-03",
    "ship": "Mein Schiff 1",
    "company": "TUI",
    "arrival": "04:00",
    "departure": "21:00"
  },
  {
    "id": "msc-splendida-0305",
    "date": "2026-05-03",
    "ship": "MSC Splendida",
    "company": "MSC",
    "arrival": "08:00",
    "departure": "15:00"
  },
  {
    "id": "ritz-carlton-ilma-0405",
    "date": "2026-05-04",
    "ship": "Ritz-Carlton Ilma",
    "company": "Ritz-Carlton",
    "arrival": "08:00",
    "departure": "22:00"
  },
  {
    "id": "marella-discovery-2-0505",
    "date": "2026-05-05",
    "ship": "Marella Discovery 2",
    "company": "Marella",
    "arrival": "06:00",
    "departure": "22:00"
  },
  {
    "id": "costa-pacifica-0505",
    "date": "2026-05-05",
    "ship": "Costa Pacifica",
    "company": "Costa",
    "arrival": "10:00",
    "departure": "22:00"
  },
  {
    "id": "mein-schiff-4-0605",
    "date": "2026-05-06",
    "ship": "Mein Schiff 4",
    "company": "TUI",
    "arrival": "04:00",
    "departure": "21:00"
  },
  {
    "id": "explorer-of-the-seas-0605",
    "date": "2026-05-06",
    "ship": "Explorer Of The Seas",
    "company": "Royal Caribbean",
    "arrival": "08:00",
    "departure": "18:00"
  },
  {
    "id": "mein-schiff-1-0805",
    "date": "2026-05-08",
    "ship": "Mein Schiff 1",
    "company": "TUI",
    "arrival": "04:00",
    "departure": "21:00"
  },
  {
    "id": "msc-grandiosa-0805",
    "date": "2026-05-08",
    "ship": "MSC Grandiosa",
    "company": "MSC",
    "arrival": "09:00",
    "departure": "21:00"
  },
  {
    "id": "aidacosma-0905",
    "date": "2026-05-09",
    "ship": "AIDAcosma",
    "company": "AIDA",
    "arrival": "05:00",
    "departure": "22:00"
  },
  {
    "id": "marella-explorer-0905",
    "date": "2026-05-09",
    "ship": "Marella Explorer",
    "company": "Marella",
    "arrival": "06:00",
    "departure": "22:00"
  },
  {
    "id": "norwegian-dawn-0905",
    "date": "2026-05-09",
    "ship": "Norwegian Dawn",
    "company": "Norwegian",
    "arrival": "07:00",
    "departure": "18:00"
  },
  {
    "id": "mein-schiff-4-1005",
    "date": "2026-05-10",
    "ship": "Mein Schiff 4",
    "company": "TUI",
    "arrival": "04:00",
    "departure": "22:00"
  },
  {
    "id": "celebrity-xcel-1005",
    "date": "2026-05-10",
    "ship": "Celebrity Xcel",
    "company": "Celebrity",
    "arrival": "08:00",
    "departure": "18:00"
  },
  {
    "id": "norwegian-dawn-1105",
    "date": "2026-05-11",
    "ship": "Norwegian Dawn",
    "company": "Norwegian",
    "arrival": "07:00",
    "departure": "21:00"
  },
  {
    "id": "silver-ray-1105",
    "date": "2026-05-11",
    "ship": "Silver Ray",
    "company": "Silversea",
    "arrival": "08:00",
    "departure": "21:00"
  },
  {
    "id": "aidastella-1205",
    "date": "2026-05-12",
    "ship": "AIDAstella",
    "company": "AIDA",
    "arrival": "05:00",
    "departure": "02:00"
  },
  {
    "id": "marella-discovery-2-1205",
    "date": "2026-05-12",
    "ship": "Marella Discovery 2",
    "company": "Marella",
    "arrival": "06:00",
    "departure": "22:00"
  },
  {
    "id": "costa-pacifica-1205",
    "date": "2026-05-12",
    "ship": "Costa Pacifica",
    "company": "Costa",
    "arrival": "10:00",
    "departure": "22:00"
  },
  {
    "id": "mein-schiff-1-1305",
    "date": "2026-05-13",
    "ship": "Mein Schiff 1",
    "company": "TUI",
    "arrival": "04:00",
    "departure": "22:00"
  },
  {
    "id": "world-traveller-1405",
    "date": "2026-05-14",
    "ship": "World Traveller",
    "company": "Atlas Ocean Voyages",
    "arrival": "08:00",
    "departure": "19:00"
  },
  {
    "id": "msc-grandiosa-1505",
    "date": "2026-05-15",
    "ship": "MSC Grandiosa",
    "company": "MSC",
    "arrival": "09:00",
    "departure": "21:00"
  },
  {
    "id": "aidacosma-1605",
    "date": "2026-05-16",
    "ship": "AIDAcosma",
    "company": "AIDA",
    "arrival": "05:00",
    "departure": "22:00"
  },
  {
    "id": "marella-explorer-1605",
    "date": "2026-05-16",
    "ship": "Marella Explorer",
    "company": "Marella",
    "arrival": "06:00",
    "departure": "22:00"
  },
  {
    "id": "sun-princess-1705",
    "date": "2026-05-17",
    "ship": "Sun Princess",
    "company": "Princess",
    "arrival": "07:00",
    "departure": "16:00"
  },
  {
    "id": "marella-discovery-2-1905",
    "date": "2026-05-19",
    "ship": "Marella Discovery 2",
    "company": "Marella",
    "arrival": "06:00",
    "departure": "22:00"
  },
  {
    "id": "costa-pacifica-1905",
    "date": "2026-05-19",
    "ship": "Costa Pacifica",
    "company": "Costa",
    "arrival": "10:00",
    "departure": "22:00"
  },
  {
    "id": "silver-ray-2005",
    "date": "2026-05-20",
    "ship": "Silver Ray",
    "company": "Silversea",
    "arrival": "08:00",
    "departure": "23:00"
  },
  {
    "id": "celebrity-xcel-2105",
    "date": "2026-05-21",
    "ship": "Celebrity Xcel",
    "company": "Celebrity",
    "arrival": "08:00",
    "departure": "18:00"
  },
  {
    "id": "harmony-of-the-seas-2205",
    "date": "2026-05-22",
    "ship": "Harmony Of The Seas",
    "company": "Royal Caribbean",
    "arrival": "07:00",
    "departure": "16:00"
  },
  {
    "id": "msc-grandiosa-2205",
    "date": "2026-05-22",
    "ship": "MSC Grandiosa",
    "company": "MSC",
    "arrival": "09:00",
    "departure": "21:00"
  },
  {
    "id": "aidacosma-2305",
    "date": "2026-05-23",
    "ship": "AIDAcosma",
    "company": "AIDA",
    "arrival": "05:00",
    "departure": "22:00"
  },
  {
    "id": "marella-explorer-2305",
    "date": "2026-05-23",
    "ship": "Marella Explorer",
    "company": "Marella",
    "arrival": "06:00",
    "departure": "22:00"
  },
  {
    "id": "norwegian-dawn-2305",
    "date": "2026-05-23",
    "ship": "Norwegian Dawn",
    "company": "Norwegian",
    "arrival": "07:00",
    "departure": "18:00"
  },
  {
    "id": "mein-schiff-1-2405",
    "date": "2026-05-24",
    "ship": "Mein Schiff 1",
    "company": "TUI",
    "arrival": "04:00",
    "departure": "22:00"
  },
  {
    "id": "norwegian-dawn-2505",
    "date": "2026-05-25",
    "ship": "Norwegian Dawn",
    "company": "Norwegian",
    "arrival": "07:00",
    "departure": "21:00"
  },
  {
    "id": "harmony-of-the-seas-2505",
    "date": "2026-05-25",
    "ship": "Harmony Of The Seas",
    "company": "Royal Caribbean",
    "arrival": "08:00",
    "departure": "16:00"
  },
  {
    "id": "azamara-journey-2505",
    "date": "2026-05-25",
    "ship": "Azamara Journey",
    "company": "Azamara",
    "arrival": "11:00",
    "departure": "19:00"
  },
  {
    "id": "marella-discovery-2-2605",
    "date": "2026-05-26",
    "ship": "Marella Discovery 2",
    "company": "Marella",
    "arrival": "06:00",
    "departure": "22:00"
  },
  {
    "id": "ms-europa-2605",
    "date": "2026-05-26",
    "ship": "ms Europa",
    "company": "Hapag-Lloyd",
    "arrival": "08:00",
    "departure": "18:00"
  },
  {
    "id": "costa-pacifica-2605",
    "date": "2026-05-26",
    "ship": "Costa Pacifica",
    "company": "Costa",
    "arrival": "10:00",
    "departure": "22:00"
  },
  {
    "id": "ms-oosterdam-2905",
    "date": "2026-05-29",
    "ship": "ms Oosterdam",
    "company": "Holland America",
    "arrival": "07:00",
    "departure": "17:00"
  },
  {
    "id": "msc-grandiosa-2905",
    "date": "2026-05-29",
    "ship": "MSC Grandiosa",
    "company": "MSC",
    "arrival": "09:00",
    "departure": "21:00"
  },
  {
    "id": "aidacosma-3005",
    "date": "2026-05-30",
    "ship": "AIDAcosma",
    "company": "AIDA",
    "arrival": "05:00",
    "departure": "22:00"
  },
  {
    "id": "marella-explorer-3005",
    "date": "2026-05-30",
    "ship": "Marella Explorer",
    "company": "Marella",
    "arrival": "06:00",
    "departure": "22:00"
  }
]